MANIFEST.in
README.md
setup.py
gdalhelpers/__init__.py
gdalhelpers.egg-info/PKG-INFO
gdalhelpers.egg-info/SOURCES.txt
gdalhelpers.egg-info/dependency_links.txt
gdalhelpers.egg-info/not-zip-safe
gdalhelpers.egg-info/requires.txt
gdalhelpers.egg-info/top_level.txt
gdalhelpers/checks/__init__.py
gdalhelpers/checks/datasource_checks.py
gdalhelpers/checks/geometry_checks.py
gdalhelpers/checks/layer_checks.py
gdalhelpers/checks/srs_checks.py
gdalhelpers/checks/values_checks.py
gdalhelpers/classes/DEM.py
gdalhelpers/classes/__init__.py
gdalhelpers/functions/__init__.py
gdalhelpers/functions/create_points_at_angles_distance.py
gdalhelpers/functions/create_points_at_angles_distance_in_direction.py
gdalhelpers/helpers/__init__.py
gdalhelpers/helpers/datasource_helpers.py
gdalhelpers/helpers/geometry_helpers.py
gdalhelpers/helpers/layer_helpers.py
gdalhelpers/helpers/math_helpers.py