Metadata-Version: 1.0
Name: gdalhelpers
Version: 0.1.7
Summary: GDAL helpers, checks, classes and functions package
Home-page: https://github.com/JanCaha/gdalhelpers
Author: Jan Caha
Author-email: jan.caha@outlook.com
License: MIT
Platform: UNKNOWN
